wzx/__init__.py
wzx/funs.py
wzx/io.py
wzx/nlp.py
wzx-0.0.4.1.17.dist-info/LICENSE
wzx-0.0.4.1.17.dist-info/METADATA
wzx-0.0.4.1.17.dist-info/WHEEL
wzx-0.0.4.1.17.dist-info/top_level.txt
wzx-0.0.4.1.17.dist-info/RECORD
