Metadata-Version: 2.1
Name: wzx
Version: 0.0.4.1.17
Summary: util
Home-page: https://zhenesis.com/
Author: Zhenxin (Jason) Wang
Author-email: wzhx.cc@gmail.com
Classifier: Programming Language :: Python :: 3
Classifier: License :: OSI Approved :: MIT License
Classifier: Operating System :: OS Independent
Requires-Python: >=3.6
License-File: LICENSE
